{
    "name": "Allu Ashok Reddy",
    "email": "allureddy4572@gmail.com",
    "mobile_number": "8610705304",
    "skills": [
        "Sdlc",
        "Analyze",
        "Linux",
        "Docker",
        "Testing",
        "Jira",
        "Windows",
        "Process",
        "Technical skills",
        "Java",
        "Shell",
        "Cloud",
        "Technical",
        "Networking",
        "Email",
        "Automation",
        "Administration",
        "Unix",
        "Aws",
        "Scrum",
        "Scripting",
        "Troubleshooting",
        "Mobile",
        "Security",
        "Ansible",
        "Agile",
        "Github",
        "Ubuntu",
        "Writing",
        "System"
    ],
    "college_name": null,
    "degree": [
        "B.Tech"
    ],
    "designation": [
        "Release Engineer",
        "DevOps Engineer in TECH MAHINDRA"
    ],
    "experience": null,
    "company_names": [
        "Amazon",
        "Unisys"
    ],
    "no_of_pages": null,
    "total_experience": 0
}