{
    "name": "CHANDRA G E-Mail:chandra.g4921@gmail.com Mobile",
    "email": "E-Mail:chandra.g4921@gmail.com",
    "mobile_number": "890 9503",
    "skills": [
        "Servers",
        "Communication",
        "Access",
        "Linux",
        "Docker",
        "Testing",
        "Installation",
        "Oracle",
        "Windows",
        "Process",
        "Technical skills",
        "Java",
        "Schedules",
        "Cloud",
        "Analysis",
        "Crm",
        "Technical",
        "Operations",
        "Account management",
        "Python",
        "International",
        "Automation",
        "Design",
        "Database",
        "Aws",
        "Unix",
        "Troubleshooting",
        "Mobile",
        "Security",
        "Updates",
        "Spark",
        "Mysql",
        "Ansible",
        "Github",
        "Writing",
        "Sales",
        "System"
    ],
    "college_name": null,
    "degree": null,
    "designation": null,
    "experience": null,
    "company_names": [
        "Oracle"
    ],
    "no_of_pages": null,
    "total_experience": 0
}