{
    "name": "Name of the Candidate Markandeyulu",
    "email": "markandeyulureddi9@gmail.com",
    "mobile_number": "8792709961",
    "skills": [
        "Testing",
        "Strategy",
        "Yaml",
        "Ansible",
        "Docker",
        "System administration",
        "Scheduling",
        "Troubleshooting",
        "Writing",
        "Electrical",
        "Automation",
        "Installation",
        "Engineering",
        "Dhcp",
        "Operations",
        "Scripting",
        "Agile",
        "Cloud",
        "Technical skills",
        "Design",
        "Shell",
        "Access",
        "System",
        "Security",
        "Aws",
        "Servers",
        "Administration",
        "Redhat",
        "Email",
        "Process",
        "Migration",
        "Electronics",
        "Linux",
        "Technical",
        "Dns",
        "Os"
    ],
    "college_name": null,
    "degree": null,
    "designation": null,
    "experience": [],
    "company_names": null,
    "no_of_pages": null,
    "total_experience": 0.0
}