{
    "name": "Rahul Tipole",
    "email": "rahultipole@gmail.com",
    "mobile_number": "8149578739",
    "skills": [
        "Retail",
        "Servers",
        "Routing",
        "English",
        "Analytics",
        "Linux",
        "Lifecycle",
        "Data collection",
        "Quality assurance",
        "Docker",
        "Jira",
        "Windows",
        "Sql",
        "Policies",
        "Process",
        "Cloud",
        "Reporting",
        "Crm",
        "Logging",
        "Technical",
        "Ai",
        "Database",
        "Design",
        "Aws",
        "Scripting",
        "Mysql",
        "Documentation",
        "System",
        "Scheduling",
        "Yaml"
    ],
    "college_name": null,
    "degree": null,
    "designation": null,
    "experience": [
        "MARCH   2019   -   PRESENT",
        "IWORK   TECHNOLOGIES   PVT.   LTD,   Pune,   Maharashtra.    -    DevOps   Engineer"
    ],
    "company_names": null,
    "no_of_pages": 4,
    "total_experience": 0.0
}