{
    "name": "RESUME SAITEJA",
    "email": "saitejavedullapalli@gmail.com",
    "mobile_number": "8639368474",
    "skills": [
        "Controls",
        "Workflow",
        "Healthcare",
        "Strategy",
        "Ansible",
        "Docker",
        "Github",
        "Money",
        "Troubleshooting",
        "Writing",
        "Policies",
        "Networking",
        "Installation",
        "Automation",
        "Scripting",
        "Agile",
        "Cloud",
        "Technical skills",
        "Shell",
        "Windows",
        "Access",
        "Moment",
        "Java",
        "Aws",
        "Servers",
        "Process",
        "Linux",
        "Technical"
    ],
    "college_name": null,
    "degree": null,
    "designation": null,
    "experience": [
        "\u27a2  Administered the automatic build process to ensure correct build execution, and resolved the",
        "build issues.",
        "\u27a2  Create users, groups and manage access controls in Jenkins.",
        "\u27a2  Configuration of various plugins for Jenkins for automation of the workflow.",
        "\u27a2",
        "Installed, configured, and integrated Maven with Jenkins."
    ],
    "company_names": null,
    "no_of_pages": 3,
    "total_experience": 0.0
}