{
    "name": "CURRICULUM VITAE",
    "email": "shikhapriyedarshi4@gmail.com",
    "mobile_number": "9650772567",
    "skills": [
        "Os",
        "Servers",
        "Engineering",
        "Access",
        "Linux",
        "System",
        "Docker",
        "Installation",
        "Cloud",
        "Analysis",
        "Technical",
        "Logging",
        "Electronics",
        "Python",
        "Automation",
        "Design",
        "Aws",
        "Electrical",
        "Troubleshooting",
        "Mobile",
        "Security",
        "Programming",
        "Ansible",
        "Saas",
        "English"
    ],
    "college_name": null,
    "degree": null,
    "designation": [
        "Linux Administrator",
        "Associate Software Engineer"
    ],
    "experience": [
        "\u2022 Used Rancher for monitoring of Kubernetes cluster",
        "\u2022 Set up logging for the kubernetes cluster in cloudwatch.",
        "\u2022 Set up the whole EKS cluster",
        "\u2022 Understanding forTerraform",
        "\u2022 Understanding of  Ansible",
        "\u2022 Understanding of Python."
    ],
    "company_names": null,
    "no_of_pages": 3,
    "total_experience": 0.0
}