{
    "name": "Saurabh Pandey",
    "email": "saurabhpandey1324@gmail.co",
    "mobile_number": "8744088748",
    "skills": [
        "Oracle",
        "Sql",
        "Java",
        "Engineering",
        "Html",
        "Css",
        "Ui",
        "Javascript",
        "Design",
        "Js",
        "English"
    ],
    "college_name": null,
    "degree": null,
    "designation": [
        "Team Member",
        "Software Engineer"
    ],
    "experience": [
        "React and Web development.",
        "Qss Techno soft",
        "Web Developer(React JS) August, 2019",
        "Software Developer(ADF) July 2018",
        "Responsibilities:",
        "1.Interact with clients and gather",
        "Business requirements and objectives.",
        "2.Design, develop and implement",
        "new integration.",
        "3.Provide innovative solutions to",
        "complex business problems.",
        "PROJECTS:",
        "1. Xseller8 (Web Site)",
        "Role Played \u2013 Frontend Design & Development",
        "Technologies Used \u2013 JavaScript, React,",
        "React-Redux, Material-UI, HTML, CSS, GraphQl.",
        "Team Member - 3",
        "2. San8tize(Web SIte).",
        "Role Played - Frontend Design & Development",
        "Technologies Used \u2013 JavaScript, React,",
        "React-Redux, Material-UI, HTML, CSS, GraphQl",
        "Team Member - 8",
        "3. GPS(Web SIte).",
        "Role Played - Frontend Design & Development",
        "Technologies Used \u2013 JavaScript, React,",
        "React-Redux, Material-UI, HTML, CSS, GraphQl",
        "Team Member - 4",
        "4. Consentrade(Web SIte).",
        "Role Played - Frontend Design & Development",
        "Technologies Used \u2013 JavaScript, React,",
        "React-Redux, Material-UI, HTML, CSS, GraphQl",
        "Team Member - 3",
        "5. Uptake Medical (Web Site)",
        "Role Played - Frontend Design & Development",
        "Technologies Used \u2013 JavaScript, React,",
        "React-Redux, Material-UI, HTML, CSS,",
        "GraphQl.",
        "Team Member - 3",
        "Tools",
        "VS Code",
        "Eclipse",
        "Oracle Adf",
        "Tool"
    ],
    "company_names": [
        "Oracle"
    ],
    "no_of_pages": 2,
    "total_experience": 0.0
}