{
    "name": "Sinha Senior",
    "email": "abhijeetsinha2003@gmail.com",
    "mobile_number": "7217394812",
    "skills": [
        "Javascript",
        "Design",
        "Html5",
        "Sales",
        "Html",
        "Css",
        "Js",
        "English",
        "Writing",
        "Mysql",
        "System",
        "Architecture",
        "Finance",
        "Java",
        "Linux",
        "Apis"
    ],
    "college_name": null,
    "degree": null,
    "designation": null,
    "experience": [
        "designing, developing, and managing complex web-based applications and",
        "internal frameworks. Specializes in Bootstrap framework, Angular framework,",
        "Spring Boot, Java and Responsive design."
    ],
    "company_names": null,
    "no_of_pages": 1,
    "total_experience": 0.0
}