{
    "name": "Pooja Rani",
    "email": "nain.pooja28@gmail.com",
    "mobile_number": "9309974724",
    "skills": [
        "Scala",
        "Testing",
        "Css",
        "Publishing",
        "English",
        "Javascript",
        "Analysis",
        "Writing",
        "Jira",
        "Continuous improvement",
        "Coding",
        "Mysql",
        "Agile",
        "Improvement",
        "Programming",
        "Design",
        "Windows",
        "Modeling",
        "Database",
        "Html",
        "User stories",
        "Linux",
        "Technical",
        "Os"
    ],
    "college_name": null,
    "degree": null,
    "designation": [
        "Software Developer"
    ],
    "experience": [
        "Project Name",
        "Dates (From - To)",
        "Employer",
        "Business / Sector",
        "Position",
        "Environment",
        "Roles and responsibilities",
        "LANGUAGES",
        "English, Hindi."
    ],
    "company_names": null,
    "no_of_pages": 2,
    "total_experience": 0.0
}