{
    "name": "VARUN SAINI",
    "email": "varun.saini2@outlook.com",
    "mobile_number": "8630682479",
    "skills": [
        "Hive",
        "Scala",
        "Analytics",
        "Linux",
        "Hadoop",
        "Etl",
        "Postgresql",
        "Oracle",
        "Sql",
        "Windows",
        "Industry experience",
        "Hbase",
        "Java",
        "Cloud",
        "Analysis",
        "Technical",
        "Api",
        "Python",
        "Automation",
        "Spark",
        "Programming",
        "Mysql",
        "Ubuntu",
        "Pyspark",
        "System"
    ],
    "college_name": null,
    "degree": [
        "BCA)"
    ],
    "designation": [
        "DATA ENGINEER"
    ],
    "experience": [
        "FEB 2019 \u2013 JUN 2019",
        "DATA ENGINEER/ANALYTICS INTERN, GENPACT HYDERABAD, TELANGANA"
    ],
    "company_names": [
        "ANALYTICS INTERN"
    ],
    "no_of_pages": 3,
    "total_experience": 0.33
}