{
    "name": "NirbhayNayal Cloud Engineer",
    "email": "Email:nirbhaynayal001@gmail.com",
    "mobile_number": "7042054569",
    "skills": [
        "Networking",
        "Technical",
        "Cloud",
        "Servers",
        "Windows",
        "Analytics",
        "Sql",
        "Dns",
        "Security",
        "Queries",
        "Design",
        "Aws",
        "System",
        "Database",
        "Engineering",
        "Os",
        "Linux",
        "Operations",
        "Process"
    ],
    "college_name": null,
    "degree": null,
    "designation": [
        "NOC engineer",
        "Cloud Engineer"
    ],
    "experience": null,
    "company_names": [
        "Amazon",
        "PROGRESSIVE INFOTECH PVT LTD"
    ],
    "no_of_pages": null,
    "total_experience": 0
}