{
    "name": "Gopal Roy Shivdarshan",
    "email": "gopal.k.roy@gmail.com",
    "mobile_number": "9199200807",
    "skills": [
        "Os",
        "Sdlc",
        "Zookeeper",
        "Analyze",
        "Access",
        "Banking",
        "Lifecycle",
        "Js",
        "Testing",
        "Repairs",
        "Oracle",
        "Sql",
        "Policies",
        "Java",
        "Cloud",
        "Rest",
        "Reporting",
        "Technical",
        "Networking",
        "Investigate",
        "Automation",
        "Troubleshooting",
        "Mobile",
        "Ansible",
        "Agile",
        "Ubuntu",
        "Lan",
        "System",
        "Xml",
        "Underwriting",
        "Hive",
        "Analytics",
        "Queries",
        "Payroll",
        "Docker",
        "Regulatory",
        "Installation",
        "Inventory",
        "Sql server",
        "Shell",
        "Operations",
        "Research",
        "Metrics",
        "Requests",
        "Python",
        "Ibm",
        "Administration",
        "Database",
        "Wifi",
        "Scripting",
        "Mysql",
        "Selenium",
        "Documentation",
        "Scheduling",
        "Analytical",
        "Servers",
        "Health",
        "Ruby",
        "Linux",
        "Hadoop",
        "Jira",
        "Windows",
        "Process",
        "Logging",
        "Salesforce",
        "Api",
        "Aws",
        "Pl/sql",
        "Openstack",
        "Nosql",
        "Dhcp",
        "Customer service",
        "Billing",
        "Mortgage",
        "Itil",
        "Application support",
        "Dns",
        "Plan",
        "Emea",
        "Crm",
        "Finance",
        "Telecom",
        "Tfs",
        "Email",
        "International",
        "Android",
        "Solaris",
        "Microsoft office",
        "Unix",
        "Security",
        "Training",
        "Github",
        "Sales",
        "Distribution",
        "Contracts",
        "English"
    ],
    "college_name": null,
    "degree": [
        "BCA Completed HOBBIES"
    ],
    "designation": [
        "Technical Support consultant L2.(US Voice) Duties and  Responsibilities Supporting  Dells US Business users and for remotely for  Desktop , Notebooks, printers and other networking devices. Technical support team responsible for Bank PC desktop, laptop configuration, mobile device"
    ],
    "experience": null,
    "company_names": [
        "Amazon",
        "Oracle",
        "Rhombus Technologies Inc"
    ],
    "no_of_pages": null,
    "total_experience": 0
}