{
    "name": "Devops Consultant",
    "email": "E-mail:narendrasysops@gmail.com",
    "mobile_number": "9191607567",
    "skills": [
        "Scripting",
        "Java",
        "Distribution",
        "Analysis",
        "Docker",
        "Technical",
        "Technical skills",
        "Cloud",
        "Shell",
        "Python",
        "Servers",
        "Automation",
        "Testing",
        "Windows",
        "Saltstack",
        "Logging",
        "Agile",
        "Ubuntu",
        "Scheduling",
        "Access",
        "Schedule",
        "Yaml",
        "Requests",
        "Security",
        "Sales",
        "Ansible",
        "Design",
        "Content",
        "Policies",
        "Aws",
        "Sdlc",
        "Unix",
        "System",
        "Software development life cycle",
        "Engineering",
        "Os",
        "Linux",
        "Operations",
        "Process",
        "Assembly"
    ],
    "college_name": null,
    "degree": null,
    "designation": [
        "4.10years.(DevOps Engineer",
        "Devops Engineer Current Location/Native Andhra Pradesh Education B.Tech"
    ],
    "experience": null,
    "company_names": [
        "Shell",
        "Candidate Name Narendra Reddy Kurri"
    ],
    "no_of_pages": null,
    "total_experience": 0
}