{
    "name": "Smruti Ranjan Mishra",
    "email": "ranjandevops1985@gmail.com",
    "mobile_number": "9607949882",
    "skills": [
        "Scripting",
        "Oracle",
        "Networking",
        "Solaris",
        "Technical",
        "Docker",
        "Test plans",
        "Active directory",
        "Cloud",
        "Shell",
        "Installation",
        "Json",
        "Compliance",
        "Migration",
        "Python",
        "Servers",
        "Automation",
        "Windows",
        "Ruby",
        "Agile",
        "Pl/sql",
        "Email",
        "Writing",
        "Administration",
        "Sql",
        "Itil",
        "Access",
        "Fabric",
        "Yaml",
        "Communication",
        "Security",
        "Perl",
        "Vmware",
        "Metrics",
        "Ansible",
        "Jira",
        "Ibm",
        "Tfs",
        "Policies",
        "Api",
        "Zookeeper",
        "Aws-cli",
        "Nosql",
        "Aws",
        "Sdlc",
        "Workflows",
        "Github",
        "Unix",
        "Telecom",
        "Documentation",
        "System",
        "Mysql",
        "Database",
        "Software development life cycle",
        "Troubleshooting",
        "Banking",
        "Green",
        "Linux",
        "Process",
        "Boto3"
    ],
    "college_name": null,
    "degree": null,
    "designation": [
        "System engineer",
        "TCS Associate Consultant"
    ],
    "experience": null,
    "company_names": [
        "Wipro",
        "Authentic Technology solutions Pvt Ltd Software trainee"
    ],
    "no_of_pages": null,
    "total_experience": 0
}