{
    "name": "RESUME Mohammad",
    "email": "azharshaikh295@gmail.com",
    "mobile_number": "996-766-1406",
    "skills": [
        "Oracle",
        "Ui",
        "Payments",
        "Training",
        "Technical",
        "Analysis",
        "Technical skills",
        "Payroll",
        "Jsp",
        "Json",
        "Servers",
        "Javascript",
        "Apis",
        "Scrum",
        "Cms",
        "Email",
        "Sql",
        "Electronics",
        "Expenses",
        "Licensing",
        "Finance",
        "Reports",
        "Jira",
        "Design",
        "Api",
        "Github",
        "Accounting",
        "Documentation",
        "System",
        "Mysql",
        "Database",
        "English",
        "Rest",
        "Java",
        "Mobile",
        "Process"
    ],
    "college_name": null,
    "degree": null,
    "designation": null,
    "experience": null,
    "company_names": [
        "Design Arena Pvt Ltd)",
        "Oracle"
    ],
    "no_of_pages": 3,
    "total_experience": 0
}