{
    "name": "Mayura Zadane Designation",
    "email": "Email:mayura19.zadane@gmail.com",
    "mobile_number": "7620824342",
    "skills": [
        "C++",
        "Improvement",
        "Communication",
        "R",
        "Engineering",
        "Analyze",
        "Linux",
        "Access",
        "Machine learning",
        "Banking",
        "Scipy",
        "Money",
        "Etl",
        "Regulatory",
        "Numpy",
        "Sql",
        "Process",
        "Windows",
        "Xgboost",
        "Content",
        "Cloud",
        "Matplotlib",
        "Analysis",
        "Seaborn",
        "Finance",
        "Algorithms",
        "Pandas",
        "Python",
        "Investigate",
        "Legal",
        "Marketing",
        "Design",
        "Aws",
        "Flask",
        "Mining",
        "Product development",
        "Modeling",
        "Mobile",
        "Nosql",
        "Lean",
        "Programming",
        "System",
        "Nltk",
        "English",
        "Data analysis"
    ],
    "college_name": null,
    "degree": null,
    "designation": null,
    "experience": null,
    "company_names": null,
    "no_of_pages": null,
    "total_experience": 0
}