{
    "name": "Sreeramakrishna SreeramakrishnaPentyala",
    "email": "sreeram4mdm@gmail.com",
    "mobile_number": "9703307088",
    "skills": [
        "Workflow",
        "Healthcare",
        "Json",
        "Sql server",
        "Pl/sql",
        "Troubleshooting",
        "Unix",
        "Oracle",
        "Warehouse",
        "Operations",
        "Scripting",
        "Agile",
        "Cloud",
        "Programming",
        "Etl",
        "Design",
        "Shell",
        "Windows",
        "Access",
        "Database",
        "System",
        "Xml",
        "Java",
        "Sql",
        "Mobile",
        "Documentation",
        "Communication",
        "Workflows",
        "Process",
        "Migration",
        "Technical",
        "Telecom",
        "Queries",
        "Analysis",
        "Conversion"
    ],
    "college_name": null,
    "degree": null,
    "designation": [
        "ETL Developer",
        "ATM Engineer",
        "MDM Developer"
    ],
    "experience": [],
    "company_names": [
        "Oracle"
    ],
    "no_of_pages": null,
    "total_experience": 0.0
}