{
    "name": "SAHIL SAMBHERWAL",
    "email": "Sahil101295s@gmail.com",
    "mobile_number": "8607877174",
    "skills": [
        "Billing",
        "Swift",
        "Servers",
        "Routing",
        "Communication",
        "Access",
        "Linux",
        "Installation",
        "Inventory",
        "Inventory management",
        "Windows",
        "Word",
        "Excel",
        "Sql",
        "Dns",
        "Shell",
        "Cloud",
        "Networking",
        "Administration",
        "Aws",
        "Scripting",
        "Troubleshooting",
        "Hardware",
        "Security",
        "Protocols",
        "Migration",
        "Documentation",
        "System",
        "Analytical",
        "Dhcp",
        "Reports",
        "Powerpoint",
        "English"
    ],
    "college_name": null,
    "degree": [
        "BCA"
    ],
    "designation": [
        "Cloud engineer Engineer",
        "\uf0fc Network Security"
    ],
    "experience": [
        "\uf0b7 Worked with MM9 information technologies Pvt. Ltd. since 15th June 2017 till 13th june 2018 as a system",
        "Administrator with handling over more than 800 users and over 550 systems and",
        "Servers, Inventory management, software, hardware, troubleshooting network (wired and wireless devices),",
        "working in company\u2019s on-premises Datacentre.Handling multiple sites across the globe,",
        "Looking after ILL connection and MPLS connection.",
        "\uf0b7 Worked as IT-Linux and cloud Administrator with Precision Tech Enterprises, Rohtak from 3rd july 2018 to 25th",
        "march 2019. Handling on cloud and on premises infrastructure",
        "AWS: working with Ec2,S3,IAM,billing, Route 53, ELB, Cloud migration etc",
        "Linux: Handing DHCP,DNS, Samba server, GIT, Apache server and users day-to-day calls and resolving within",
        "given SLA.",
        "\uf0b7 Working with Televisory India Pvt. Ltd., Gurgaon from 1st April 2019 till Present as IT-Cloud engineer Engineer",
        "and working with Windows and Linux Server and Desktop and troublshooting and resolving the issues over",
        "chat or remote or on call or Tickets. Handling AWS cloud and deploying applications and servers on cloud",
        "with the custom AMIs by migration of on-premises servers as well as on any virtual tool and configuring",
        "Cloudwatch for monitoring. Working with VPC,E2 Instances, S3 bucket, Route-53, Cloudwatch, ASG, ELB and",
        "other monitoring tools and reading the logs and resolving the issues."
    ],
    "company_names": [
        "Televisory India Pvt. Ltd."
    ],
    "no_of_pages": 2,
    "total_experience": 0.0
}