{
    "name": "Ankit Bhor ankit.bhor56@gmail.com",
    "email": "ankit.bhor56@gmail.com",
    "mobile_number": "9131871192",
    "skills": [
        "Testing",
        "Intranet",
        "English",
        "Purchasing",
        "Networking",
        "Vendors",
        "Coding",
        "Website",
        "Engineering",
        "Positioning",
        "Programming",
        "Design",
        "Real estate",
        "Windows",
        "Database",
        "System",
        "Java",
        "Sql",
        "Mobile",
        "Servers",
        "Communication",
        "Transportation",
        "Payments",
        "Process",
        "Invoices",
        "Jsp",
        "Technical",
        "Analysis",
        "Logistics"
    ],
    "college_name": null,
    "degree": [
        "B.E."
    ],
    "designation": [
        "Software Engineer"
    ],
    "experience": null,
    "company_names": null,
    "no_of_pages": null,
    "total_experience": 0
}