{
    "name": "CURRICULUM VITAE",
    "email": "Email:-kumarneerajnit@gmail.com",
    "mobile_number": "9151644543",
    "skills": [
        "Testing",
        "C++",
        "Css",
        "English",
        "Javascript",
        "Selenium",
        "Coding",
        "Automation",
        "Physics",
        "Engineering",
        "Mathematics",
        "Technical skills",
        "Programming",
        "P",
        "Chemistry",
        "Html",
        "Java",
        "C",
        "Communication",
        "Technical"
    ],
    "college_name": null,
    "degree": null,
    "designation": null,
    "experience": null,
    "company_names": null,
    "no_of_pages": 2,
    "total_experience": 0
}