{
    "name": "Pawan Singh",
    "email": "pawan24091988@gmail.com",
    "mobile_number": "9191361079",
    "skills": [
        "Testing",
        "English",
        "Scheduling",
        "Jira",
        "Coding",
        "Rest",
        "Engineering",
        "Oracle",
        "Audit",
        "Api",
        "Apex",
        "Windows",
        "Ui",
        "Database",
        "System",
        "Compliance",
        "Java",
        "Billing",
        "Documentation",
        "Fulfillment",
        "Email",
        "Jsp",
        "Technical",
        "International"
    ],
    "college_name": null,
    "degree": [
        "B. Tech",
        "M. Tech"
    ],
    "designation": [
        "Sr. Engineering",
        "Software Developer"
    ],
    "experience": [
        "framework.",
        "Technical Skill Set",
        "Language & Frameworks",
        "Software Tools",
        "Operating System",
        "Data Base",
        "Source Control Management (SCM) Tools",
        "Application Monitoring Tool",
        "Application Documentation Tool",
        "Application Testing Tool",
        ":",
        ":",
        ":",
        ":",
        ":",
        ":",
        ":",
        ":",
        "Spring, Hibernate, SpringBoot, MicroServices",
        "Core Java, JSP, Servlet, Maven, jenkins, hiroku,",
        "Eclipse, NetBeans,",
        "Windows XP/7/10",
        "Oracle, Postgres",
        "SVN, GIT",
        "Jira, Java Melody, SonarLint Tool",
        "Swagger, Microsoft Teams",
        "Junit, Jmeter",
        "Currently Working with SDG Software India Pvt Ltd as a Senior Software Engineer.",
        "Key Responsibilities",
        "\uf0a7  Understanding client\u2019s requirements and working towards fulfillment of the desired objectives in",
        "structured form along with the team members.",
        "Planning and scheduling activities to ensure completion of the project within the time.",
        "Presenting findings in a concise manner with appropriate \u201cWay Forward\u201d or recommendations.",
        "\uf0a7",
        "\uf0a7",
        "\uf0a7  As an Engineering Analyst, responsible for coding of the various modules, unit testing and to",
        "ensure smooth integration with other modules.",
        "Employer details",
        "Sr. No.  Name of Employer",
        "SDG Software India Pvt. Ltd",
        "Period",
        "Designation",
        "From",
        "Jul-2019",
        "To",
        "Present",
        "1",
        "2",
        "3",
        "4",
        "5",
        "Rsystems International Ltd.",
        "Sep-2018",
        "Jun-2019",
        "Qualtech-Consultants Pvt Ltd",
        "Apex TG India Pvt Ltd",
        "RateGain IT Solution Pvt. Ltd",
        "Jan -2015",
        "Jul-2014",
        "Jun -2010",
        "Sep-2018",
        "Jan-2015",
        "Nov-2011",
        "Sr. Software",
        "Engineer",
        "Sr. Software",
        "Engineer",
        "Sr. Engineering",
        "Analyst",
        "Software Developer",
        "SDE"
    ],
    "company_names": [
        "Apex TG India Pvt Ltd",
        "Aadhaar validation",
        "oracle",
        "RateGain IT Solution Pvt. Ltd"
    ],
    "no_of_pages": 3,
    "total_experience": 0.0
}