{
    "name": "VEERANJANEYA REDDY YAGNAM",
    "email": "veeranjaneya.reddy@ojas-it.com",
    "mobile_number": "8328117823",
    "skills": [
        "Software development life cycle",
        "Css",
        "Javascript",
        "Coding",
        "Sdlc",
        "Automation",
        "Engineering",
        "Mysql",
        "Pattern",
        "Technical skills",
        "Architecture",
        "Programming",
        "Design",
        "Windows",
        "Inventory",
        "Database",
        "Html",
        "System",
        "Java",
        "Sql",
        "Mobile",
        "Servers",
        "Customer requirements",
        "Communication",
        "Visual",
        "Email",
        "Process",
        "Jsp",
        "Migration",
        "Technical"
    ],
    "college_name": null,
    "degree": null,
    "designation": null,
    "experience": null,
    "company_names": null,
    "no_of_pages": null,
    "total_experience": 0
}