{
    "name": "Anil Ambati",
    "email": "E-mail:aakr739753@gmail.com",
    "mobile_number": "9052191053",
    "skills": [
        "Nosql",
        "Mysql",
        "Python",
        "Api",
        "Jira",
        "Unix",
        "Java",
        "Process",
        "Analytics",
        "Oracle",
        "Db2",
        "Windows",
        "Scripting",
        "Spark",
        "Writing",
        "Etl",
        "Hadoop",
        "Pyspark",
        "Analyze",
        "Queries",
        "Shell",
        "Hive",
        "Agile",
        "Scala",
        "Warehouse",
        "Linux",
        "Operating systems"
    ],
    "college_name": null,
    "degree": null,
    "designation": [
        "Software Developer"
    ],
    "experience": null,
    "company_names": [
        "Oracle"
    ],
    "no_of_pages": null,
    "total_experience": 0
}