{
    "name": "AQUIBAHMAD ITProfessional AnIndependentandself",
    "email": "aquibalshaikh@gmail.com",
    "mobile_number": "9192357861",
    "skills": [
        "Github",
        "Research",
        "English",
        "Jira",
        "Try",
        "Docker",
        "Security",
        "Communication",
        "Linux",
        "Ansible",
        "Aws",
        "System"
    ],
    "college_name": null,
    "degree": null,
    "designation": null,
    "experience": null,
    "company_names": null,
    "no_of_pages": null,
    "total_experience": 0
}