{
    "name": "Ravi Pratap Singh Bhadoriya",
    "email": "ravipratap604@gmail.com",
    "mobile_number": "7756939029",
    "skills": [
        "Healthcare",
        "Python",
        "Jira",
        "Banking",
        "Docker",
        "Automation",
        "Ansible",
        "Windows",
        "Scripting",
        "Analysis",
        "Administration",
        "Workflows",
        "Database",
        "Health",
        "Cloud",
        "Email",
        "System",
        "Agile",
        "Aws",
        "Linux",
        "Mobile",
        "Technical",
        "Servers"
    ],
    "college_name": null,
    "degree": null,
    "designation": null,
    "experience": [
        "in both on premise and cloud infrastructure.",
        "Career Profile",
        "Infosys Ltd (August 2019 - till date)",
        "\u27a2",
        "\u27a2  Marcomm Essentials  Pvt Ltd (July 2017- August 2019)"
    ],
    "company_names": [
        "Infosys",
        "Amazon",
        "Infosys Ltd"
    ],
    "no_of_pages": 3,
    "total_experience": 2.08
}