{
    "name": "Resume Vijay Arun Gajdhane",
    "email": "E-Mail:-vijaygajdhane7@gmail.com",
    "mobile_number": "8149230662",
    "skills": [
        "Mysql",
        "Matplotlib",
        "Python",
        "English",
        "Flask",
        "Sales",
        "Content",
        "Process",
        "Numpy",
        "Transactions",
        "Algorithms",
        "Finance",
        "Analytics",
        "Engineering",
        "Mango db",
        "C",
        "Html",
        "Css",
        "Windows",
        "Nltk",
        "Database",
        "Testing",
        "Analyze",
        "Ms excel",
        "System",
        "Word",
        "Sql",
        "Quality control",
        "Excel",
        "Sci",
        "Matlab",
        "Pandas",
        "Communication",
        "Linux",
        "Seaborn",
        "Technical",
        "Consulting"
    ],
    "college_name": null,
    "degree": null,
    "designation": null,
    "experience": null,
    "company_names": null,
    "no_of_pages": null,
    "total_experience": 0
}