{
    "name": "Vinkal Ghodasra",
    "email": "Vinkal.ghodasra957@gmail.com",
    "mobile_number": "200 7401",
    "skills": [
        "Marketing",
        "Nosql",
        "Healthcare",
        "Apis",
        "Api",
        "English",
        "Unix",
        "Java",
        "Data analytics",
        "Scheduling",
        "Reporting",
        "Banking",
        "Process",
        "Publishing",
        "Analytics",
        "Oracle",
        "Engineering",
        "Automation",
        "Hbase",
        "Migration",
        "Scripting",
        "Tv",
        "Spark",
        "Analysis",
        "Design",
        "Writing",
        "Etl",
        "Testing",
        "Hadoop",
        "Database",
        "Cloud",
        "Rest",
        "Regulatory",
        "Shell",
        "System",
        "Sql",
        "Queries",
        "Hive",
        "Soap",
        "Operations",
        "Scala",
        "Telecom",
        "Linux",
        "Reports",
        "Architecture",
        "Technical"
    ],
    "college_name": null,
    "degree": null,
    "designation": [
        "Team Lead"
    ],
    "experience": null,
    "company_names": null,
    "no_of_pages": null,
    "total_experience": 0
}