{
    "name": "ABHISHEK SONI",
    "email": "kewlsethis@gmail.com",
    "mobile_number": "9654273987",
    "skills": [
        "Javascript",
        "Test cases",
        "Green",
        "Aws",
        "Distribution",
        "Ubuntu",
        "Automation",
        "Swift",
        "Deposits",
        "Unix",
        "Rest",
        "Architecture",
        "Selenium",
        "Billing",
        "Debugging",
        "Sql",
        "Matrix",
        "Electronics",
        "Communication",
        "Python",
        "Scheduling",
        "Project plan",
        "Banking",
        "Hp alm",
        "Shell",
        "Scrum",
        "Programming",
        "Ios",
        "Cloud",
        "Strategy",
        "Policies",
        "Logging",
        "Reporting",
        "Mobile",
        "Telecom",
        "Technical",
        "Oracle",
        "Schedules",
        "Servers",
        "Networking",
        "Database",
        "Process",
        "Api",
        "Db2",
        "Github",
        "Scripting",
        "System",
        "Docker",
        "Java",
        "Openstack",
        "Sap",
        "Jira",
        "Plan",
        "Ibm",
        "Linux",
        "Documentation",
        "Administration",
        "Payments",
        "Finance",
        "Writing",
        "Web services",
        "Testing",
        "Robot",
        "Lifecycle",
        "Json",
        "Governance",
        "Analysis",
        "Ansible",
        "Access",
        "Schedule",
        "Android",
        "Windows"
    ],
    "college_name": null,
    "degree": null,
    "designation": [
        "Software Engineer",
        "Automation Lead       Client                          Department of Work and Pensions (Govt)"
    ],
    "experience": [],
    "company_names": [
        "Infosys"
    ],
    "no_of_pages": null,
    "total_experience": 0.0
}