{
    "name": "ANNU KUMAR",
    "email": "annukmr484@gmail.com",
    "mobile_number": "7875187037",
    "skills": [
        "Python",
        "Api",
        "Jira",
        "Scheduling",
        "Engineering",
        "Analytics",
        "Docker",
        "Training",
        "Migration",
        "Ansible",
        "Scripting",
        "Jupyter",
        "Programming",
        "Github",
        "Writing",
        "Anaconda",
        "Hadoop",
        "Cloud",
        "Rest",
        "Queries",
        "Shell",
        "Hive",
        "Agile",
        "Open source",
        "Pandas",
        "Warehouse",
        "Technical",
        "Servers",
        "Consulting"
    ],
    "college_name": null,
    "degree": [
        "BE \u2013 Computer Engineering"
    ],
    "designation": [
        "DATA ENGINEERING"
    ],
    "experience": null,
    "company_names": [
        "Sinhgad Institute of Technology /"
    ],
    "no_of_pages": 1,
    "total_experience": 0
}