{
    "name": "HARSHIT RAWAL",
    "email": "hrawal99@gmail.com",
    "mobile_number": "8460475819",
    "skills": [
        "Test cases",
        "Automation",
        "Sales",
        "Security",
        "C",
        "Electronics",
        "Communication",
        "Python",
        "Project plan",
        "Scrum",
        "Programming",
        "English",
        "Cloud",
        "Strategy",
        "Technical",
        "Photography",
        "Certification",
        "Product launch",
        "Reports",
        "Research",
        "Assembly",
        "Hardware",
        "Agile",
        "Engineering",
        "System",
        "Fabrication",
        "Plan",
        "Linux",
        "Marketing",
        "Testing",
        "Schedule",
        "Visual",
        "Design",
        "Windows"
    ],
    "college_name": null,
    "degree": [
        "B.E. Electronics & Communication"
    ],
    "designation": [
        "\u201cLead"
    ],
    "experience": [
        "1.  System Level Solutions (India) Pvt Ltd, Anand, Gujarat | Aug 2019 \u2013 Current",
        "Position: Product Owner",
        "Roles:",
        "\u25aa  Conducting daily scrum with team members",
        "\u25aa  Provide direction to team during project life cycle as Agile product Owner",
        "\u25aa  Ensure that every team member has pre-defined task during sprint",
        "\u25aa  Translating product roadmap into manageable product backlog and prepare the user stories.",
        "\u25aa  Prioritize product backlog and supports the release and sprint planning exercise.",
        "\u25aa  Closely work with project management team to track product feature backlogs during sprint.",
        "\u25aa  Set and prioritize backlogs as per the business needs.",
        "\u25aa  Actively participate to mitigate issue faced during sprint to achieve release milestone.",
        "\u25aa  Plan with all stakeholders for product release.",
        "\u25aa  Conduct market research for preparing product roadmap and work with marketing and sales",
        "team for making strategy.",
        "Product Ownership:",
        "Smart Home Automation",
        "\u25aa  Definition:  IoT  and  cloud-based  technology  provides  simple,  affordable,  and  engaging",
        "integrates  multiple",
        "solutions  for  customers  of Home  Automation.  This  ecosystem",
        "devices/sensors into a network and thus provides end-to-end security to the enterprises.",
        "\u25aa  Team Members: 12",
        "\u25aa  Status: Product Launch in market",
        "Internal",
        "LoRa Concentrator Board",
        "\u25aa  Definition: Based on LoRa Technology, this hardware product provides complete support",
        "of communication between nodes and Linux host platform with additional feature of GPS.",
        "\u25aa  Team Members: 6",
        "\u25aa  Status: Product Launch in market",
        "EV (Electric Vehicle) Charger with Controller",
        "\u25aa  Definition: Control Application with commands to provide flexibility offer for controlling",
        "EV charging.",
        "\u25aa  Team Members: 5",
        "\u25aa  Status: Ongoing",
        "2.  Aimtron Electronics Pvt Ltd, Vadodara, Gujarat | March 2016 \u2013 Aug2019",
        "Position: Project Engineer",
        "Roles:"
    ],
    "company_names": null,
    "no_of_pages": 4,
    "total_experience": 0.0
}