{
    "name": "MD SHAHNAWAZ KHAN AWS Cloud Engineer",
    "email": "khan786shahnawaz@gmail.com",
    "mobile_number": "7827484999",
    "skills": [
        "Installation",
        "Distribution",
        "Mysql",
        "Python",
        "Api",
        "Jira",
        "Unix",
        "Java",
        "Reporting",
        "Ubuntu",
        "Perl",
        "Process",
        "Vmware",
        "Docker",
        "Automation",
        "Php",
        "Program development",
        "Migration",
        "Ansible",
        "Scripting",
        "Analysis",
        "Design",
        "Writing",
        "Dns",
        "Website",
        "Database",
        "Redhat",
        "Cloud",
        "Click",
        "Email",
        "Shell",
        "Queries",
        "System",
        "Operations",
        "Security",
        "Linux",
        "Aws",
        "Technical",
        "Servers"
    ],
    "college_name": null,
    "degree": null,
    "designation": [
        "Linux Administrator",
        "Cloud Engineer",
        "NOC Engineer",
        "System Administrator",
        "DevOps Engineer"
    ],
    "experience": null,
    "company_names": [
        "Shell"
    ],
    "no_of_pages": null,
    "total_experience": 0
}