{
    "name": "Ajay Pratap",
    "email": "ajaypr2707@gmail.com",
    "mobile_number": "7905192664",
    "skills": [
        "Postgresql",
        "Testing",
        "Reporting",
        "Automation",
        "Windows",
        "Design",
        "Saas",
        "Selenium",
        "Ubuntu",
        "System",
        "Mysql",
        "Database",
        "Sql",
        "Website",
        "Java",
        "Click",
        "Api"
    ],
    "college_name": null,
    "degree": null,
    "designation": null,
    "experience": [
        "Company  :  Neumeric  Technologies  Pvt.  Ltd.(Nov  2019-Present)",
        "Position : Quality Analyst(Automation)",
        "Role :  I worked as an Automation Tester and also supported Manual Testing as well. My responsibility",
        "includes creating testcases from requirements and then automate them through selenium",
        "and reporting the defects.",
        "Company  :  Smalsus  InfoLabs  Pvt.  Ltd.(March  2018  -  Sep  2019)",
        "Position : Test engineer",
        "Role :  I am being responsible for testing a website name \u2019SURVEY\u2019.It is a Saas based Customer Suc-",
        "cess Management(CSM) project. I have tested that website thoroughly by making different test",
        "cases.I have tested the all aspects of that application like design, properties, permissions etc.",
        "QA",
        "AJAY PRATAP SINGH- CV",
        "1"
    ],
    "company_names": null,
    "no_of_pages": 2,
    "total_experience": 0.0
}