{
    "name": "KRISHAN BISHT",
    "email": "krishanbisht23@gmail.com",
    "mobile_number": "9916455696",
    "skills": [
        "Testing",
        "Ecommerce",
        "Seo",
        "English",
        "Debugging",
        "Selenium",
        "Jira",
        "Automation",
        "Test cases",
        "Scripting",
        "Agile",
        "Api",
        "Usability",
        "Erp",
        "Windows",
        "P",
        "Crm",
        "Database",
        "Sales",
        "System",
        "Security",
        "Java",
        "Sql",
        "Mobile",
        "Communication",
        "Email",
        "Reports",
        "Process"
    ],
    "college_name": null,
    "degree": [
        "BCA",
        "MCA"
    ],
    "designation": [
        "Manual and Automation)"
    ],
    "experience": null,
    "company_names": null,
    "no_of_pages": null,
    "total_experience": 0
}